LICENSE.txt
MANIFEST.in
README.rst
setup.py
swingleism.py
swingleism4.egg-info/PKG-INFO
swingleism4.egg-info/SOURCES.txt
swingleism4.egg-info/dependency_links.txt
swingleism4.egg-info/entry_points.txt
swingleism4.egg-info/requires.txt
swingleism4.egg-info/top_level.txt