Metadata-Version: 1.0
Name: swingleism4
Version: 0.1.0
Summary: swingleism, yo
Home-page: http://github.com/johnswingle44/swingleism/
Author: John Swingle
Author-email: johnswingle44@gmail.com
License: MIT
Platform: UNKNOWN
Classifier: Development Status :: 4 - Beta
Classifier: Environment :: Console
Classifier: License :: OSI Approved :: MIT License
Classifier: Operating System :: OS Independent
Classifier: Topic :: Utilities
